loci/__init__.py
loci/loci.py
loci-0.1.0.dist-info/METADATA
loci-0.1.0.dist-info/WHEEL
loci-0.1.0.dist-info/top_level.txt
loci-0.1.0.dist-info/RECORD
