Metadata-Version: 2.1
Name: loci
Version: 0.1.0
Summary: Implementation of the LOCI outlier detection algorithm in Python
Home-page: https://github.com/Cloudy10/loci
Author: Claudio Schill
Author-email: claudio.schill@icloud.com
License: MIT
Platform: UNKNOWN
Classifier: Programming Language :: Python :: 3
Classifier: License :: OSI Approved :: MIT License
Classifier: Operating System :: OS Independent
Requires-Dist: numpy
Requires-Dist: scipy
